django_generate_series/__init__.py
django_generate_series/admin.py
django_generate_series/apps.py
django_generate_series/base.py
django_generate_series/exceptions.py
django_generate_series/models.py
django_generate_series/urls.py
django_generate_series/views.py
django_generate_series/static/css/django_directed.css
django_generate_series/static/js/django_directed.js
django_generate_series/templates/django_generate_series/base.html
django_generate_series/templatetags/__init__.py
django_generate_series-0.4.5.dist-info/AUTHORS.md
django_generate_series-0.4.5.dist-info/LICENSE
django_generate_series-0.4.5.dist-info/METADATA
django_generate_series-0.4.5.dist-info/WHEEL
django_generate_series-0.4.5.dist-info/top_level.txt
django_generate_series-0.4.5.dist-info/RECORD
