Metadata-Version: 2.1
Name: django-generate-series
Version: 0.4.5
Summary: Use Postgres' generate_series to create sequences with Django's ORM
Home-page: https://github.com/jacklinke/django-generate-series/
Author: Jack Linke
Author-email: jack@watervize.com
License: Apache Software License
Project-URL: Documentation, https://django-generate-series.readthedocs.io/en/latest/
Project-URL: Source, https://github.com/jacklinke/django-generate-series/
Project-URL: Tracker, https://github.com/jacklinke/django-generate-series/issues
Keywords: django-generate-series,graph,tree,dag,network,directed,acyclic,postgres,cte
Platform: UNKNOWN
Classifier: Development Status :: 3 - Alpha
Classifier: Intended Audience :: Developers
Classifier: License :: OSI Approved :: Apache Software License
Classifier: Programming Language :: Python
Classifier: Programming Language :: Python :: 3.7
Classifier: Programming Language :: Python :: 3.8
Classifier: Programming Language :: Python :: 3.9
Classifier: Programming Language :: Python :: 3.10
Classifier: Operating System :: OS Independent
Classifier: Topic :: Software Development :: Libraries
Classifier: Topic :: Database
Classifier: Topic :: Utilities
Classifier: Environment :: Web Environment
Classifier: Framework :: Django
Classifier: Framework :: Django :: 2.2
Classifier: Framework :: Django :: 3.0
Classifier: Framework :: Django :: 3.1
Classifier: Framework :: Django :: 3.2
Requires-Python: >=3.7, <4
License-File: LICENSE
License-File: AUTHORS.md
Requires-Dist: django (>=2.2)
Requires-Dist: pydantic (>=1.8)
Provides-Extra: all
